{
  "": "",
  "ALL": "",
  "Admin": "Admin",
  "Admin Panel": "Admin Panel",
  "Advanced Frontend": "Advanced Frontend",
  "App": "",
  "Articl": "Articl",
  "Article": "Article",
  "Article not found": "Article not found",
  "Authorization": "Authorization",
  "Choose a country": "Choose a country",
  "Choose a currency": "Choose a currency",
  "Comments": "Comments",
  "Create article": "Create article",
  "Create new article": "Create new article",
  "ECONOMICS": "",
  "Edit article with ID = ": "Edit article with ID = ",
  "Enter comment text": "Enter comment text",
  "Error": "Error",
  "Error login or password": "Error login or password",
  "IT": "",
  "Log_In": "Log_In",
  "Log_Out": "Log_Out",
  "No Comments": "No Comments",
  "Not found page": "Not found page",
  "Password": "Password",
  "Profile": "Profile",
  "Read more": "Read more",
  "Recommends": "Recommends",
  "SCIENCE": "",
  "Send": "Send",
  "Sort": "Sort",
  "Throw error": "Throw error",
  "Update Page": "Update Page",
  "Username": "Username",
  "Vadim Astapenko": "Vadim Astapenko",
  "Vadim Astapenko App": "Vadim Astapenko App",
  "Статья не найдена": "Статья не найдена"
}
